gusantong/__init__.py
gusantong/server.py
gusantong/aastocks/__init__.py
gusantong/aastocks/aastocks.py
gusantong/data/__init__.py
gusantong/data/price.py
gusantong/eastmoney/__init__.py
gusantong/eastmoney/eastmoney.py
gusantong/gelonghui/__init__.py
gusantong/gelonghui/gelonghui.py
gusantong/jin10/__init__.py
gusantong/jin10/jin10.py
gusantong/sina/__init__.py
gusantong/sina/sina.py
gusantong/utils/sign_util.py
gusantong/utils/user_agent_util.py
gusantong/wallstreetcn/__init__.py
gusantong/wallstreetcn/wallstreetcn.py
gusantong/zhitongcaijing/__init__.py
gusantong/zhitongcaijing/zhitongcaijing.py
mcp_gusantong-1.0.3.dist-info/METADATA
mcp_gusantong-1.0.3.dist-info/WHEEL
mcp_gusantong-1.0.3.dist-info/entry_points.txt
mcp_gusantong-1.0.3.dist-info/licenses/LICENSE
mcp_gusantong-1.0.3.dist-info/RECORD
