Metadata-Version: 2.4
Name: mcp-gusantong
Version: 1.0.3
Summary: Add your description here
License-File: LICENSE
Requires-Python: >=3.13
Requires-Dist: aiohttp>=3.12.14
Requires-Dist: beautifulsoup4>=4.13.4
Requires-Dist: brotli>=1.1.0
Requires-Dist: build>=1.2.2.post1
Requires-Dist: httpx>=0.28.1
Requires-Dist: mcp>=1.12.0
Requires-Dist: twine>=6.1.0
